apnspy/__init__.py
apnspy/apns.py
apnspy/apnspy.py
apnspy/cli.py
apnspy-0.0.7.dist-info/LICENSE
apnspy-0.0.7.dist-info/METADATA
apnspy-0.0.7.dist-info/WHEEL
apnspy-0.0.7.dist-info/top_level.txt
apnspy-0.0.7.dist-info/RECORD
