Metadata-Version: 2.1
Name: apnspy
Version: 0.0.7
Summary: Python Distribution Utilities
Home-page: https://github.com/yehchilai/apnspy
Author: Yeh-chi Lai
Author-email: 
License: Apache 2.0
Platform: UNKNOWN
Classifier: Programming Language :: Python
Classifier: Programming Language :: Python :: 2.7
Classifier: Programming Language :: Python :: 3.7
Requires-Python: >=2.7, >=3.7
Requires-Dist: hyper
Requires-Dist: PyJWT
Requires-Dist: cryptography
